README.md
setup.py
spacexpypi/__init__.py
spacexpypi.egg-info/PKG-INFO
spacexpypi.egg-info/SOURCES.txt
spacexpypi.egg-info/dependency_links.txt
spacexpypi.egg-info/top_level.txt