Metadata-Version: 2.1
Name: spacexpypi
Version: 0.0.12
Summary: SpaceX API wrapper.
Home-page: https://github.com/djtimca/spacex-api
Author: Tim Empringham
Author-email: tim.empringham@live.ca
License: apache-2.0
Download-URL: https://github.com/djtimca/spacex-api/archive/v_012.tar.gz
Keywords: SpaceX,Launch,Roadster
Platform: UNKNOWN
Classifier: Development Status :: 3 - Alpha
Classifier: Intended Audience :: Developers
Classifier: Topic :: Software Development :: Build Tools
Classifier: License :: OSI Approved :: Apache Software License
Classifier: Programming Language :: Python :: 3
Classifier: Programming Language :: Python :: 3.4
Classifier: Programming Language :: Python :: 3.5
Classifier: Programming Language :: Python :: 3.6
Requires-Python: >=3.6
